backbones_unet/__init__.py
backbones_unet/model/__init__.py
backbones_unet/model/losses.py
backbones_unet/model/unet.py
backbones_unet/utils/__init__.py
backbones_unet/utils/dataset.py
backbones_unet/utils/reproducibility.py
backbones_unet/utils/trainer.py
pretrained_backbones_unet-0.0.1.dist-info/LICENSE
pretrained_backbones_unet-0.0.1.dist-info/METADATA
pretrained_backbones_unet-0.0.1.dist-info/WHEEL
pretrained_backbones_unet-0.0.1.dist-info/top_level.txt
pretrained_backbones_unet-0.0.1.dist-info/RECORD
