Metadata-Version: 2.1
Name: pretrained-backbones-unet
Version: 0.0.1
Summary: A small example package
Home-page: https://github.com/mberkay0/pretrained-backbones-unet
Author: Berkay Mayali
Author-email: Example Author <author@example.com>
License: MIT
Project-URL: Homepage, https://github.com/pypa/sampleproject
Project-URL: Bug Tracker, https://github.com/pypa/sampleproject/issues
Keywords: machine-learning,deep-learning,pytorch,vision,semantic-segmentation,image-pixel-classification,object-detection,convnext,unet
Classifier: Programming Language :: Python :: 3
Classifier: License :: OSI Approved :: MIT License
Classifier: Operating System :: OS Independent
Requires-Python: >=3.7
License-File: LICENSE
Requires-Dist: timm (==0.6.12)
Requires-Dist: torch (>=1.13.1)
